SeleniumLibraryExtension/__init__.py
SeleniumLibraryExtension/version.py
SeleniumLibraryExtension/base/__init__.py
SeleniumLibraryExtension/base/contextpatch.py
SeleniumLibraryExtension/config/__init__.py
SeleniumLibraryExtension/config/settings.py
SeleniumLibraryExtension/decorators/__init__.py
SeleniumLibraryExtension/decorators/doc_inherit.py
SeleniumLibraryExtension/keywords/__init__.py
SeleniumLibraryExtension/keywords/elements.py
SeleniumLibraryExtension/keywords/waiting.py
SeleniumLibraryExtension-0.0.7.dist-info/DESCRIPTION.rst
SeleniumLibraryExtension-0.0.7.dist-info/METADATA
SeleniumLibraryExtension-0.0.7.dist-info/RECORD
SeleniumLibraryExtension-0.0.7.dist-info/WHEEL
SeleniumLibraryExtension-0.0.7.dist-info/metadata.json
SeleniumLibraryExtension-0.0.7.dist-info/top_level.txt
