Metadata-Version: 2.0
Name: SeleniumLibraryExtension
Version: 0.0.7
Summary: A Extension of Selenium Library 3.0.0+
Home-page: https://github.com/WandyYing/SeleniumLibraryExtension
Author: Ying Jun
Author-email: wandy1208@gmail.com
License: Apache Software License
Platform: any
Classifier: Development Status :: 5 - Production/Stable
Classifier: License :: OSI Approved :: Apache Software License
Classifier: Operating System :: OS Independent
Classifier: Programming Language :: Python
Classifier: Programming Language :: Python :: 2
Classifier: Programming Language :: Python :: 3
Classifier: Topic :: Software Development :: Testing
Classifier: Framework :: Robot Framework
Classifier: Framework :: Robot Framework :: Library
Requires-Dist: selenium (>=2.8.0)
Requires-Dist: robotframework (>=2.8.7)
Requires-Dist: robotframework-seleniumlibrary (==3.0.1)
